[
  {
    "username": "rileybrown",
    "nickname": "Riley Brown",
    "text": "RT @brycent: Want to do a vibe coding iPhone app session while flying home \n\nSomeone shill me their personal favorite app for vibe coding m…",
    "quoted_tweet": null,
    "url": "https://twitter.com/rileybrown/status/2059052532148896030",
    "time": "2026-05-26 07:22",
    "id_str": "2059052532148896030",
    "is_retweet": true
  },
  {
    "username": "rileybrown",
    "nickname": "Riley Brown",
    "text": "RT @rileybrown: @brycent Vibecoding mobile apps was made illegal by Apple. \n\nBut there is a new method they cannot block which works with a…",
    "quoted_tweet": null,
    "url": "https://twitter.com/rileybrown/status/2059057139260543172",
    "time": "2026-05-26 07:40",
    "id_str": "2059057139260543172",
    "is_retweet": true
  },
  {
    "username": "vasuman",
    "nickname": "Vasu",
    "text": "https://t.co/kynR4879ab",
    "quoted_tweet": null,
    "url": "https://twitter.com/vasuman/status/2059042300094001302",
    "time": "2026-05-26 06:41",
    "id_str": "2059042300094001302",
    "is_retweet": false
  },
  {
    "username": "venturetwins",
    "nickname": "Venture Twins",
    "text": "Thanks all for the incredibly helpful tips! And please keep them coming - I’ll upgrade for future videos.\n\nSo far, I’ve realized everything I thought I knew about lighting was wrong 😅\n\nFirst video will be going live tomorrow here:\nhttps://t.co/b8TFIvYrdU",
    "quoted_tweet": null,
    "url": "https://twitter.com/venturetwins/status/2059054684422488491",
    "time": "2026-05-26 07:31",
    "id_str": "2059054684422488491",
    "is_retweet": false
  },
  {
    "username": "oran_ge",
    "nickname": "oran_ge",
    "text": "AI 让软件开发的第一版变得极其容易\n但是真正难的是后面的100个版本\n而且越到后面越难怎么回事....\n软件工程依然有很多事情要做",
    "quoted_tweet": null,
    "url": "https://twitter.com/oran_ge/status/2059051338613531069",
    "time": "2026-05-26 07:17",
    "id_str": "2059051338613531069",
    "is_retweet": false
  }
]