[
  {
    "username": "elonmusk",
    "nickname": "马斯克",
    "text": "RT @XFreeze: Grok is officially the ultimate wingman 😂\n\nStop embarrassing yourself trying to decode mixed signals. Run those texts through…",
    "quoted_tweet": null,
    "url": "https://twitter.com/elonmusk/status/2038349839088697836",
    "time": "2026-03-30 04:17",
    "id_str": "2038349839088697836",
    "is_retweet": true
  },
  {
    "username": "dotey",
    "nickname": "宝玉",
    "text": "飞机大战\nhttps://t.co/2J4mBwzq0T",
    "quoted_tweet": null,
    "url": "https://twitter.com/dotey/status/2038345575418991103",
    "time": "2026-03-30 04:00",
    "id_str": "2038345575418991103",
    "is_retweet": false
  }
]