[
  {
    "username": "aleabitoreddit",
    "nickname": "Serenity",
    "text": "As for $LPK: Maybe $3B-$5B seems reasonable when they fully volume ramp if I had to guess. \n\nFeels more asymmetrical to me personally since it's just a waiting game and they have the customers for glass substrates. \n\nSmall machine supplier chokepoints usually cap out from TAM",
    "quoted_tweet": null,
    "url": "https://twitter.com/aleabitoreddit/status/2069005921318281566",
    "time": "2026-06-22 18:33",
    "created_at": "Mon Jun 22 10:33:46 +0000 2026",
    "id_str": "2069005921318281566",
    "is_retweet": false
  },
  {
    "username": "aleabitoreddit",
    "nickname": "Serenity",
    "text": "That’s for you to decide.\n\nBut just throwing this out there:\n\nIf $AAOI hits projections, that’s over 800%+ Y/Y growth, and $5.6B revenue annualized off $12.8B MC.\n\nMy guess is that the $471m/month will keep going up as demand seems to scale exponentially into 2028.\n\nI’d expect",
    "quoted_tweet": null,
    "url": "https://twitter.com/aleabitoreddit/status/2069062745308254434",
    "time": "2026-06-22 22:19",
    "created_at": "Mon Jun 22 14:19:34 +0000 2026",
    "id_str": "2069062745308254434",
    "is_retweet": false
  },
  {
    "username": "aleabitoreddit",
    "nickname": "Serenity",
    "text": "Wow, $SPCX is now down over $583B in MC...\n\nSince Jim Cramer gave a bullish call at $210. Pretty amazing to witness tbh. \n\nInverse Cramer would have returned ~21% in 3 trading days, outperforming a year in your largest indexes? https://t.co/IhNtFAH99s",
    "quoted_tweet": null,
    "url": "https://twitter.com/aleabitoreddit/status/2069068801329774691",
    "time": "2026-06-22 22:43",
    "created_at": "Mon Jun 22 14:43:38 +0000 2026",
    "id_str": "2069068801329774691",
    "is_retweet": false
  },
  {
    "username": "elonmusk",
    "nickname": "马斯克",
    "text": "RT @cb_doge: BREAKING: SpaceX just received an investment-grade credit rating from Fitch for its new bond offering.\n\n• Fitch gave SpaceX a…",
    "quoted_tweet": null,
    "url": "https://twitter.com/elonmusk/status/2069066240669180283",
    "time": "2026-06-22 22:33",
    "created_at": "Mon Jun 22 14:33:27 +0000 2026",
    "id_str": "2069066240669180283",
    "is_retweet": true
  },
  {
    "username": "elonmusk",
    "nickname": "马斯克",
    "text": "RT @XFreeze: Neuralink now has its 26th recipient\n\nSgt. Lee Marten, @Canuckula, is a Vancouver Police Sergeant, cyclist, and ALS patient wh…",
    "quoted_tweet": null,
    "url": "https://twitter.com/elonmusk/status/2069066419602424224",
    "time": "2026-06-22 22:34",
    "created_at": "Mon Jun 22 14:34:10 +0000 2026",
    "id_str": "2069066419602424224",
    "is_retweet": true
  },
  {
    "username": "elonmusk",
    "nickname": "马斯克",
    "text": "RT @XFreeze: The Falcon program has now delivered more mass to orbit in recent years than the rest of the world combined and more individua…",
    "quoted_tweet": null,
    "url": "https://twitter.com/elonmusk/status/2069066928556069040",
    "time": "2026-06-22 22:36",
    "created_at": "Mon Jun 22 14:36:11 +0000 2026",
    "id_str": "2069066928556069040",
    "is_retweet": true
  },
  {
    "username": "elonmusk",
    "nickname": "马斯克",
    "text": "RT @brivael: 1/ Regardez cette courbe.  \nC’est la fréquence du terme « white supremacy » dans la presse américaine (travaux de David Rozado…",
    "quoted_tweet": null,
    "url": "https://twitter.com/elonmusk/status/2069073531799752902",
    "time": "2026-06-22 23:02",
    "created_at": "Mon Jun 22 15:02:26 +0000 2026",
    "id_str": "2069073531799752902",
    "is_retweet": true
  },
  {
    "username": "elonmusk",
    "nickname": "马斯克",
    "text": "RT @C_3C_3: The Media and Left worked together to create the “white supremacy” narrative.\n\nThey had to create the lie.\n\nThey had to create…",
    "quoted_tweet": null,
    "url": "https://twitter.com/elonmusk/status/2069073565089980709",
    "time": "2026-06-22 23:02",
    "created_at": "Mon Jun 22 15:02:34 +0000 2026",
    "id_str": "2069073565089980709",
    "is_retweet": true
  },
  {
    "username": "elonmusk",
    "nickname": "马斯克",
    "text": "RT @MartinSellner_: Es gibt keine Massenproteste mehr gegen Remigration. \nAber überall in Europa gibt es Demos für Remigration. \n\nDer linke…",
    "quoted_tweet": null,
    "url": "https://twitter.com/elonmusk/status/2069073745965162607",
    "time": "2026-06-22 23:03",
    "created_at": "Mon Jun 22 15:03:17 +0000 2026",
    "id_str": "2069073745965162607",
    "is_retweet": true
  },
  {
    "username": "elonmusk",
    "nickname": "马斯克",
    "text": "RT @TheRabbitHole: Simple science https://t.co/2UxPBafbj6",
    "quoted_tweet": null,
    "url": "https://twitter.com/elonmusk/status/2069075733821936089",
    "time": "2026-06-22 23:11",
    "created_at": "Mon Jun 22 15:11:11 +0000 2026",
    "id_str": "2069075733821936089",
    "is_retweet": true
  },
  {
    "username": "vitalikbuterin",
    "nickname": "V神",
    "text": "RT @aerugoettinea: 1. Intro\n\nVitalik recently wrote about where the EF should go; Aya added a note to explain how we got here, and why. I’l…",
    "quoted_tweet": null,
    "url": "https://twitter.com/vitalikbuterin/status/2069026413462663206",
    "time": "2026-06-22 19:55",
    "created_at": "Mon Jun 22 11:55:12 +0000 2026",
    "id_str": "2069026413462663206",
    "is_retweet": true
  },
  {
    "username": "a16z",
    "nickname": "a16z",
    "text": "We're thrilled to lead Prosper's $30M Series A.\n\nHealthcare runs on the office landline: staff in headsets, scheduling patient visits while sitting on hold with insurance companies, typing into the EHR one field at a time.\n\nNone of it is medicine, and all of it decides whether https://t.co/qC57FvX60m",
    "quoted_tweet": null,
    "url": "https://twitter.com/a16z/status/2069054233702449425",
    "time": "2026-06-22 21:45",
    "created_at": "Mon Jun 22 13:45:45 +0000 2026",
    "id_str": "2069054233702449425",
    "is_retweet": false
  },
  {
    "username": "a16z",
    "nickname": "a16z",
    "text": "Orbits are now battlefields, and it’s time we admitted it.\n\nRussia tested an anti-satellite missile in 2021, hacked a commercial satellite in 2022, jammed GPS throughout the Ukraine conflict, tailed an NRO satellite with a potential “counterspace weapon” in 2024, and is https://t.co/LTqCvwrnvL",
    "quoted_tweet": null,
    "url": "https://twitter.com/a16z/status/2069069428260770144",
    "time": "2026-06-22 22:46",
    "created_at": "Mon Jun 22 14:46:07 +0000 2026",
    "id_str": "2069069428260770144",
    "is_retweet": false
  },
  {
    "username": "tuturetom",
    "nickname": "TutureTom",
    "text": "RT @OpenDesignHQ: Open Design AMR now supports GLM 5.2.\n\nBuild with a new generation of intelligence in your design workflow. https://t.co/…",
    "quoted_tweet": null,
    "url": "https://twitter.com/tuturetom/status/2069001927182938607",
    "time": "2026-06-22 18:17",
    "created_at": "Mon Jun 22 10:17:54 +0000 2026",
    "id_str": "2069001927182938607",
    "is_retweet": true
  },
  {
    "username": "tuturetom",
    "nickname": "TutureTom",
    "text": "RT @OpenDesignHQ: Now supported: Kimi 2.7 in Open Design AMR.\n\nTry it in your next design workflow. https://t.co/wQcKsPTbjs",
    "quoted_tweet": null,
    "url": "https://twitter.com/tuturetom/status/2069009480881180822",
    "time": "2026-06-22 18:47",
    "created_at": "Mon Jun 22 10:47:55 +0000 2026",
    "id_str": "2069009480881180822",
    "is_retweet": true
  },
  {
    "username": "tuturetom",
    "nickname": "TutureTom",
    "text": "RT @QiongYu1999: We hit 68,000 🌟 GitHub stars in 7 weeks.\nWe replaced human PR review with a loop. Median time-to-merge dropped to 3.4 hour…",
    "quoted_tweet": null,
    "url": "https://twitter.com/tuturetom/status/2069009810490593712",
    "time": "2026-06-22 18:49",
    "created_at": "Mon Jun 22 10:49:13 +0000 2026",
    "id_str": "2069009810490593712",
    "is_retweet": true
  },
  {
    "username": "tuturetom",
    "nickname": "TutureTom",
    "text": "RT @OpenDesignHQ: We tried GLM 5.2 inside Open Design’s built-in AMR.\n\nInput:\n- a reference website link\n- one simple prompt\n\nOutput:\n- a n…",
    "quoted_tweet": null,
    "url": "https://twitter.com/tuturetom/status/2069043724210900997",
    "time": "2026-06-22 21:03",
    "created_at": "Mon Jun 22 13:03:59 +0000 2026",
    "id_str": "2069043724210900997",
    "is_retweet": true
  },
  {
    "username": "lijigang",
    "nickname": "李继刚",
    "text": "problem &gt; solutions",
    "quoted_tweet": null,
    "url": "https://twitter.com/lijigang/status/2069007895988195512",
    "time": "2026-06-22 18:41",
    "created_at": "Mon Jun 22 10:41:37 +0000 2026",
    "id_str": "2069007895988195512",
    "is_retweet": false
  },
  {
    "username": "seclink",
    "nickname": "seclink",
    "text": "RT @seclink: 如果有朋友最近在找工作，可以私信我聊聊看。\n我这边收录了蛮多正在招人的大厂岗位的，也许有帮助。\n另外，阿里园区隔壁的生态园，\n蛮多公司也有新岗位放出来，\n从阿里离职后，若能加入另一家阿里前同事成立的公司，\n融入氛围和认同感会好一点，相互信任也会多一些。",
    "quoted_tweet": null,
    "url": "https://twitter.com/seclink/status/2069030788457181685",
    "time": "2026-06-22 20:12",
    "created_at": "Mon Jun 22 12:12:35 +0000 2026",
    "id_str": "2069030788457181685",
    "is_retweet": true
  },
  {
    "username": "icreatelife",
    "nickname": "icreatelife",
    "text": "I'm working on a community zine \"Gallery of the Future\". To take part:\n\n1. Submit your work (link in comments)\n2. Repost this \n3. Collaborate with others \n \nThe link is to Firefly Boards, free tool, to generate 5 images and 2 videos daily with different AI models \n\nAllOnBoards https://t.co/XxCmap58Io",
    "quoted_tweet": null,
    "url": "https://twitter.com/icreatelife/status/2069071216095146120",
    "time": "2026-06-22 22:53",
    "created_at": "Mon Jun 22 14:53:14 +0000 2026",
    "id_str": "2069071216095146120",
    "is_retweet": false
  },
  {
    "username": "icreatelife",
    "nickname": "icreatelife",
    "text": "How to participate: \n\n1. Submit your work here. You can add existing work or generate it right there (for free if you don't have a subscription). \n\nhttps://t.co/vzjHjGasyg\n\nOthers can collaborate with your work, so you need to be okay with others remixing your work with AI",
    "quoted_tweet": null,
    "url": "https://twitter.com/icreatelife/status/2069071746322333853",
    "time": "2026-06-22 22:55",
    "created_at": "Mon Jun 22 14:55:20 +0000 2026",
    "id_str": "2069071746322333853",
    "is_retweet": false
  },
  {
    "username": "icreatelife",
    "nickname": "icreatelife",
    "text": "So cool to see the zine is coming alive in real time. \n@GlennHasABeard is working on his art right now. https://t.co/2OoD49tNOo",
    "quoted_tweet": null,
    "url": "https://twitter.com/icreatelife/status/2069074306865217806",
    "time": "2026-06-22 23:05",
    "created_at": "Mon Jun 22 15:05:30 +0000 2026",
    "id_str": "2069074306865217806",
    "is_retweet": false
  },
  {
    "username": "justinsuntron",
    "nickname": "孙宇晨",
    "text": "Stablecoins are becoming payment infrastructure.  USDT on TRON is already proving that at scale every day.",
    "quoted_tweet": null,
    "url": "https://twitter.com/justinsuntron/status/2069006100041732364",
    "time": "2026-06-22 18:34",
    "created_at": "Mon Jun 22 10:34:29 +0000 2026",
    "id_str": "2069006100041732364",
    "is_retweet": false
  }
]